pydatum/__init__.py
pydatum/datum.py
pydatum/range.py
pydatum-1.2.0.dist-info/LICENSE
pydatum-1.2.0.dist-info/METADATA
pydatum-1.2.0.dist-info/WHEEL
pydatum-1.2.0.dist-info/top_level.txt
pydatum-1.2.0.dist-info/RECORD
